<annotation>
	<folder>images</folder>
	<filename>687.jpeg</filename>
	<path>/home/adriana/deteccion_objetos/images/687.jpeg</path>
	<source>
		<database>Unknown</database>
	</source>
	<size>
		<width>0</width>
		<height>0</height>
		<depth>3</depth>
	</size>
	<segmented>0</segmented>
	<object>
		<name>Elefante</name>
		<pose>Unspecified</pose>
		<truncated>0</truncated>
		<difficult>0</difficult>
		<bndbox>
			<xmin>12</xmin>
			<ymin>203</ymin>
			<xmax>106</xmax>
			<ymax>275</ymax>
		</bndbox>
	</object>
	<object>
		<name>Elefante</name>
		<pose>Unspecified</pose>
		<truncated>0</truncated>
		<difficult>0</difficult>
		<bndbox>
			<xmin>152</xmin>
			<ymin>212</ymin>
			<xmax>252</xmax>
			<ymax>281</ymax>
		</bndbox>
	</object>
	<object>
		<name>Elefante</name>
		<pose>Unspecified</pose>
		<truncated>0</truncated>
		<difficult>0</difficult>
		<bndbox>
			<xmin>298</xmin>
			<ymin>226</ymin>
			<xmax>387</xmax>
			<ymax>274</ymax>
		</bndbox>
	</object>
	<object>
		<name>Elefante</name>
		<pose>Unspecified</pose>
		<truncated>0</truncated>
		<difficult>0</difficult>
		<bndbox>
			<xmin>421</xmin>
			<ymin>221</ymin>
			<xmax>493</xmax>
			<ymax>280</ymax>
		</bndbox>
	</object>
</annotation>
